prospector_profile_utils/__init__.py
prospector_profile_utils/autofix.yaml
prospector_profile_utils/base-all.yaml
prospector_profile_utils/base-less-strict.yaml
prospector_profile_utils/base.yaml
prospector_profile_utils/c2cwsgiutils.yaml
prospector_profile_utils/fix.yaml
prospector_profile_utils/no-design-checks.yaml
prospector_profile_utils/pre-commit-no-autofix.yaml
prospector_profile_utils/pre-commit.yaml
prospector_profile_utils/tests.yaml
prospector_profile_utils-1.26.5.dist-info/LICENSE
prospector_profile_utils-1.26.5.dist-info/METADATA
prospector_profile_utils-1.26.5.dist-info/WHEEL
prospector_profile_utils-1.26.5.dist-info/RECORD
