Metadata-Version: 2.3
Name: prospector-profile-utils
Version: 1.26.5
Summary: Some utility Prospector profiles.
License: BSD-2-Clause
Author: Stéphane Brunner
Author-email: stephane.brunner@gmail.com
Classifier: Development Status :: 5 - Production/Stable
Classifier: Intended Audience :: Developers
Classifier: License :: OSI Approved :: BSD License
Classifier: Operating System :: OS Independent
Classifier: Programming Language :: Python
Classifier: Programming Language :: Python :: 3
Requires-Dist: prospector[with-mypy,with-ruff] (>=1.14.0)
Project-URL: Bug Tracker, https://github.com/sbrunner/prospector-profile-utils/issues
Project-URL: Repository, https://github.com/sbrunner/prospector-profile-utils
